[{"name":"KE","cityList":[{"name":"Nyahururu","link":"http://en.wikipedia.org/wiki/Nyahururu"},{"name":"Narok","link":"http://en.wikipedia.org/wiki/Narok"},{"name":"Kitui","link":"http://en.wikipedia.org/wiki/Kitui"},{"name":"Karuri","link":"http://en.wikipedia.org/wiki/Karuri"},{"name":"Webuye","link":"http://en.wikipedia.org/wiki/Webuye"},{"name":"Maralal","link":"http://en.wikipedia.org/wiki/Maralal"},{"name":"Makueni","link":"http://en.wikipedia.org/wiki/Makueni"},{"name":"Mombasa","link":"http://en.wikipedia.org/wiki/Mombasa"},{"name":"Eldoret","link":"http://en.wikipedia.org/wiki/Eldoret"},{"name":"Kisumu","link":"http://en.wikipedia.org/wiki/Kisumu"},{"name":"Nairobi","link":"http://en.wikipedia.org/wiki/Nairobi"},{"name":"Malindi","link":"http://en.wikipedia.org/wiki/Malindi"},{"name":"Nakuru","link":"http://en.wikipedia.org/wiki/Nakuru"},{"name":"Meru","link":"http://en.wikipedia.org/wiki/Meru"},{"name":"Isiolo","link":"http://en.wikipedia.org/wiki/Isiolo"},{"name":"Kitale","link":"http://en.wikipedia.org/wiki/Kitale"},{"name":"Embu","link":"http://en.wikipedia.org/wiki/Embu"},{"name":"Garissa","link":"http://en.wikipedia.org/wiki/Garissa"},{"name":"Lamu","link":"http://en.wikipedia.org/wiki/Lamu"}]},{"name":"KG","cityList":[{"name":"Isfana","link":"http://en.wikipedia.org/wiki/Isfana"},{"name":"Jalal-Abad","link":"http://en.wikipedia.org/wiki/Jalal-Abad"},{"name":"Balykchy","link":"http://en.wikipedia.org/wiki/Balykchy"},{"name":"Cholpon-Ata","link":"http://en.wikipedia.org/wiki/Cholpon-Ata"},{"name":"Kara-Balta","link":"http://en.wikipedia.org/wiki/Kara-Balta"},{"name":"Tokmok","link":"http://en.wikipedia.org/wiki/Tokmok"},{"name":"Kant","link":"http://en.wikipedia.org/wiki/Kant"},{"name":"Uzgen","link":"http://en.wikipedia.org/wiki/Uzgen"},{"name":"At-Bashi","link":"http://en.wikipedia.org/wiki/At-Bashi"},{"name":"Pokrovka","link":"http://en.wikipedia.org/wiki/Kyzyl-Suu"},{"name":"Bishkek","link":"http://en.wikipedia.org/wiki/Bishkek"},{"name":"Talas","link":"http://en.wikipedia.org/wiki/Talas"},{"name":"Karakol","link":"http://en.wikipedia.org/wiki/Karakol"},{"name":"Tash-Kumyr","link":"http://en.wikipedia.org/wiki/Tash-Kumyr"},{"name":"Toktogul","link":"http://en.wikipedia.org/wiki/Toktogul"}]},{"name":"KH","cityList":[{"name":"Ta Khmau","link":"http://en.wikipedia.org/wiki/Ta_Khmao_%28city%29"},{"name":"Stoeng Treng","link":"http://en.wikipedia.org/wiki/Stung_Treng"},{"name":"Pursat","link":"http://en.wikipedia.org/wiki/Pursat"},{"name":"Phumi Veal Sre","link":"http://en.wikipedia.org/wiki/Phumi+Veal+Sre"},{"name":"Lumphat","link":"http://en.wikipedia.org/wiki/Lumphat"},{"name":"Phnom Penh","link":"http://en.wikipedia.org/wiki/Phnom+Penh"},{"name":"Batdambang","link":"http://en.wikipedia.org/wiki/Batdambang"},{"name":"Kampot","link":"http://en.wikipedia.org/wiki/Kampot"}]},{"name":"KM","cityList":[{"name":"Moutsamoudou","link":"http://en.wikipedia.org/wiki/Moutsamoudou"}]},{"name":"KP","cityList":[{"name":"Ongjin","link":"http://en.wikipedia.org/wiki/Ongjin"},{"name":"Kosan","link":"http://en.wikipedia.org/wiki/Kosan"},{"name":"Haeju","link":"http://en.wikipedia.org/wiki/Haeju"},{"name":"Sil-li","link":"http://en.wikipedia.org/wiki/Sil-li"},{"name":"Tongchon-up","link":"http://en.wikipedia.org/wiki/Tongchon-up"},{"name":"Sungho 1-tong","link":"http://en.wikipedia.org/wiki/Sungho+1-tong"},{"name":"Sunan","link":"http://en.wikipedia.org/wiki/Sunan_International_Airport"},{"name":"Songnim","link":"http://en.wikipedia.org/wiki/Songrim"},{"name":"Sinmak","link":"http://en.wikipedia.org/wiki/Sinmak"},{"name":"Sariwon","link":"http://en.wikipedia.org/wiki/Sariwon"},{"name":"Nampo","link":"http://en.wikipedia.org/wiki/Nampho"},{"name":"Kangdong-up","link":"http://en.wikipedia.org/wiki/Kangdong-up"},{"name":"Hungnam","link":"http://en.wikipedia.org/wiki/H%C5%ADngnam"},{"name":"Hukkyo-ri","link":"http://en.wikipedia.org/wiki/Hukkyo-ri"},{"name":"Hoeyang","link":"http://en.wikipedia.org/wiki/Hoeyang"},{"name":"Changyon","link":"http://en.wikipedia.org/wiki/Changyon"},{"name":"Chaeryong-up","link":"http://en.wikipedia.org/wiki/Chaeryong-up"},{"name":"Ayang-ni","link":"http://en.wikipedia.org/wiki/Ayang-ni"},{"name":"Anju","link":"http://en.wikipedia.org/wiki/Anju_%28city%29"},{"name":"Anak","link":"http://en.wikipedia.org/wiki/Anak"},{"name":"Uiju","link":"http://en.wikipedia.org/wiki/Uiju"},{"name":"Sonbong","link":"http://en.wikipedia.org/wiki/Sonbong"},{"name":"Sinuiju","link":"http://en.wikipedia.org/wiki/Sinuiju"},{"name":"Onsong","link":"http://en.wikipedia.org/wiki/Onsong"},{"name":"Kilju","link":"http://en.wikipedia.org/wiki/Kilju_%28North_Korea%29"},{"name":"Kapsan-up","link":"http://en.wikipedia.org/wiki/Kapsan-up"},{"name":"Kanggye-si","link":"http://en.wikipedia.org/wiki/Kanggye"},{"name":"Hoeryong","link":"http://en.wikipedia.org/wiki/Hoeryong"},{"name":"Pyongyang","link":"http://en.wikipedia.org/wiki/Pyongyang"},{"name":"Yonan-up","link":"http://en.wikipedia.org/wiki/Yonan-up"},{"name":"Wonsan","link":"http://en.wikipedia.org/wiki/Wonsan"},{"name":"Sinanju","link":"http://en.wikipedia.org/wiki/Sinanju"},{"name":"Samho-rodongjagu","link":"http://en.wikipedia.org/wiki/Samho-rodongjagu"},{"name":"Kusong","link":"http://en.wikipedia.org/wiki/Kusong"},{"name":"Kujang-up","link":"http://en.wikipedia.org/wiki/Kujang-up"},{"name":"Kowon-up","link":"http://en.wikipedia.org/wiki/Kowon-up"},{"name":"Hwangju-up","link":"http://en.wikipedia.org/wiki/Hwangju-up"},{"name":"Chunghwa","link":"http://en.wikipedia.org/wiki/Chunghwa"},{"name":"Chongju","link":"http://en.wikipedia.org/wiki/Chongju"},{"name":"Anbyon-up","link":"http://en.wikipedia.org/wiki/Anbyon-up"},{"name":"Yuktae-dong","link":"http://en.wikipedia.org/wiki/Yuktae-dong"},{"name":"Sakchu-up","link":"http://en.wikipedia.org/wiki/Sakchu-up"},{"name":"Yonggwang-up","link":"http://en.wikipedia.org/wiki/Yonggwang-up"},{"name":"Nanam","link":"http://en.wikipedia.org/wiki/Nanam"},{"name":"Namyang-dong","link":"http://en.wikipedia.org/wiki/Namyang-dong"},{"name":"Najin","link":"http://en.wikipedia.org/wiki/Najin"},{"name":"Musan-up","link":"http://en.wikipedia.org/wiki/Musan-up"},{"name":"Kyongsong","link":"http://en.wikipedia.org/wiki/Kyongsong"},{"name":"Iwon-up","link":"http://en.wikipedia.org/wiki/Iwon-up"},{"name":"Hyesan-dong","link":"http://en.wikipedia.org/wiki/Hyesan-dong"},{"name":"Hongwon","link":"http://en.wikipedia.org/wiki/Hongwon"},{"name":"Aoji-ri","link":"http://en.wikipedia.org/wiki/Aoji-ri"}]},{"name":"KR","cityList":[{"name":"Neietsu","link":"http://en.wikipedia.org/wiki/Neietsu"},{"name":"Reiko","link":"http://en.wikipedia.org/wiki/Reiko"},{"name":"Yeoju","link":"http://en.wikipedia.org/wiki/Yeoju"},{"name":"Yanggu","link":"http://en.wikipedia.org/wiki/Yanggu"},{"name":"Mungyeong","link":"http://en.wikipedia.org/wiki/Mungyeong"},{"name":"Kurye","link":"http://en.wikipedia.org/wiki/Kurye"},{"name":"Cheongsong gun","link":"http://en.wikipedia.org/wiki/Cheongsong"},{"name":"Chinchon","link":"http://en.wikipedia.org/wiki/Jincheon"},{"name":"Hwawon","link":"http://en.wikipedia.org/wiki/Hwawon"},{"name":"Enjitsu","link":"http://en.wikipedia.org/wiki/Enjitsu"},{"name":"yeoncheongun","link":"http://en.wikipedia.org/wiki/yeoncheongun"},{"name":"Yangpyong","link":"http://en.wikipedia.org/wiki/Yangpyeong"},{"name":"Yangju","link":"http://en.wikipedia.org/wiki/Yangju"},{"name":"Wanju","link":"http://en.wikipedia.org/wiki/Wanju"},{"name":"Waegwan","link":"http://en.wikipedia.org/wiki/Waegwan"},{"name":"Vijongbu","link":"http://en.wikipedia.org/wiki/Uijeongbu"},{"name":"Taesal-li","link":"http://en.wikipedia.org/wiki/Taesal-li"},{"name":"Puan","link":"http://en.wikipedia.org/wiki/Buan"},{"name":"Asan","link":"http://en.wikipedia.org/wiki/Asan"},{"name":"Munsan","link":"http://en.wikipedia.org/wiki/Munsan"},{"name":"Kwangju","link":"http://en.wikipedia.org/wiki/Gwangju%2C_Gyeonggi"},{"name":"Kuri","link":"http://en.wikipedia.org/wiki/Guri"},{"name":"Kunwi","link":"http://en.wikipedia.org/wiki/Kunwi"},{"name":"Kinzan","link":"http://en.wikipedia.org/wiki/Geumsan"},{"name":"Kumi","link":"http://en.wikipedia.org/wiki/Kumi"},{"name":"Kyosai","link":"http://en.wikipedia.org/wiki/Geoje"},{"name":"Gimcheon","link":"http://en.wikipedia.org/wiki/Gimcheon"},{"name":"Gapyeong","link":"http://en.wikipedia.org/wiki/Gapyeong_County"},{"name":"Hwaseong","link":"http://en.wikipedia.org/wiki/Hwaseong,_Gyeonggi"},{"name":"Hwacheon","link":"http://en.wikipedia.org/wiki/Hwacheon"},{"name":"Hongsung","link":"http://en.wikipedia.org/wiki/Hongseong"},{"name":"Hongchon","link":"http://en.wikipedia.org/wiki/Hongcheon"},{"name":"jin-angun","link":"http://en.wikipedia.org/wiki/jin-angun"},{"name":"Changsu","link":"http://en.wikipedia.org/wiki/Jangsu"},{"name":"Yonmu","link":"http://en.wikipedia.org/wiki/Yonmu"},{"name":"Tonghae","link":"http://en.wikipedia.org/wiki/Tonghae"},{"name":"Pubal","link":"http://en.wikipedia.org/wiki/Pubal"},{"name":"Seongnam","link":"http://en.wikipedia.org/wiki/Seongnam"},{"name":"Hwado","link":"http://en.wikipedia.org/wiki/Hwado"},{"name":"Naeso","link":"http://en.wikipedia.org/wiki/Naeso"},{"name":"Changnyeong","link":"http://en.wikipedia.org/wiki/Changnyeong"},{"name":"Heung-hai","link":"http://en.wikipedia.org/wiki/Heung-hai"},{"name":"Eisen","link":"http://en.wikipedia.org/wiki/Eisen"},{"name":"Taisen-ri","link":"http://en.wikipedia.org/wiki/Boryeong"},{"name":"Jenzan","link":"http://en.wikipedia.org/wiki/Jenzan"},{"name":"Songwon","link":"http://en.wikipedia.org/wiki/Songwon"},{"name":"Fuyo","link":"http://en.wikipedia.org/wiki/Buyeo_County"},{"name":"Beolgyo","link":"http://en.wikipedia.org/wiki/Beolgyo"},{"name":"Kosong","link":"http://en.wikipedia.org/wiki/Kosong"},{"name":"Kijang","link":"http://en.wikipedia.org/wiki/Kijang"},{"name":"Imsil","link":"http://en.wikipedia.org/wiki/Imsil"},{"name":"Hayang","link":"http://en.wikipedia.org/wiki/Hayang"},{"name":"Gaigeturi","link":"http://en.wikipedia.org/wiki/Gaigeturi"},{"name":"Sinhyeon","link":"http://en.wikipedia.org/wiki/Sinhyeon"},{"name":"Ungsang","link":"http://en.wikipedia.org/wiki/Ungsang"},{"name":"Sinan","link":"http://en.wikipedia.org/wiki/Sinan"},{"name":"Andong","link":"http://en.wikipedia.org/wiki/Andong"},{"name":"Ulsan","link":"http://en.wikipedia.org/wiki/Ulsan"},{"name":"Busan","link":"http://en.wikipedia.org/wiki/Busan"},{"name":"Ansan","link":"http://en.wikipedia.org/wiki/Ansan"},{"name":"Daegu","link":"http://en.wikipedia.org/wiki/Daegu"},{"name":"Kimhae","link":"http://en.wikipedia.org/wiki/Kimhae"},{"name":"Wonju","link":"http://en.wikipedia.org/wiki/Wonju"},{"name":"Masan","link":"http://en.wikipedia.org/wiki/Masan"},{"name":"Iksan","link":"http://en.wikipedia.org/wiki/Iksan"},{"name":"Chinju","link":"http://en.wikipedia.org/wiki/Chinju"},{"name":"Bucheon","link":"http://en.wikipedia.org/wiki/Bucheon"},{"name":"Gwangju","link":"http://en.wikipedia.org/wiki/Gwangju"},{"name":"Jeju","link":"http://en.wikipedia.org/wiki/Jeju"},{"name":"Yangsan","link":"http://en.wikipedia.org/wiki/Yangsan"},{"name":"Cheongju","link":"http://en.wikipedia.org/wiki/Cheongju"},{"name":"Chuncheon","link":"http://en.wikipedia.org/wiki/Chuncheon"},{"name":"Goyang","link":"http://en.wikipedia.org/wiki/Goyang"},{"name":"Hoko","link":"http://en.wikipedia.org/wiki/Hoko"},{"name":"Yanggok","link":"http://en.wikipedia.org/wiki/Yanggok"},{"name":"Tenan","link":"http://en.wikipedia.org/wiki/Tenan"},{"name":"Kwangyang","link":"http://en.wikipedia.org/wiki/Kwangyang"},{"name":"Yesan","link":"http://en.wikipedia.org/wiki/Yesan"},{"name":"Kongju","link":"http://en.wikipedia.org/wiki/Kongju"},{"name":"Chinhae","link":"http://en.wikipedia.org/wiki/Chinhae"},{"name":"Kunsan","link":"http://en.wikipedia.org/wiki/Kunsan"},{"name":"Moppo","link":"http://en.wikipedia.org/wiki/Moppo"},{"name":"Anyang","link":"http://en.wikipedia.org/wiki/Anyang"},{"name":"Jeonju","link":"http://en.wikipedia.org/wiki/Jeonju"},{"name":"Reisui","link":"http://en.wikipedia.org/wiki/Reisui"},{"name":"Sogcho","link":"http://en.wikipedia.org/wiki/Sogcho"},{"name":"Hanam","link":"http://en.wikipedia.org/wiki/Hanam"},{"name":"Kang-neung","link":"http://en.wikipedia.org/wiki/Kang-neung"},{"name":"Sunchun","link":"http://en.wikipedia.org/wiki/Sunchun"},{"name":"Miryang","link":"http://en.wikipedia.org/wiki/Miryang"},{"name":"Sangju","link":"http://en.wikipedia.org/wiki/Sangju"},{"name":"Suisan","link":"http://en.wikipedia.org/wiki/Suisan"},{"name":"Osan","link":"http://en.wikipedia.org/wiki/Osan"},{"name":"Ichon","link":"http://en.wikipedia.org/wiki/Ichon"},{"name":"Kimje","link":"http://en.wikipedia.org/wiki/Kimje"},{"name":"Nonsan","link":"http://en.wikipedia.org/wiki/Nonsan"},{"name":"Yong-dong","link":"http://en.wikipedia.org/wiki/Yong-dong"},{"name":"Goseong","link":"http://en.wikipedia.org/wiki/Goseong"},{"name":"Eisen","link":"http://en.wikipedia.org/wiki/Eisen"},{"name":"Keizan","link":"http://en.wikipedia.org/wiki/Keizan"},{"name":"Nangen","link":"http://en.wikipedia.org/wiki/Nangen"},{"name":"Haenam","link":"http://en.wikipedia.org/wiki/Haenam"},{"name":"Hwasun","link":"http://en.wikipedia.org/wiki/Hwasun"},{"name":"Naju","link":"http://en.wikipedia.org/wiki/Naju"},{"name":"Kyonju","link":"http://en.wikipedia.org/wiki/Kyonju"},{"name":"Kwangmyong","link":"http://en.wikipedia.org/wiki/Kwangmyong"},{"name":"Kochang","link":"http://en.wikipedia.org/wiki/Kochang"},{"name":"Taebaek","link":"http://en.wikipedia.org/wiki/Taebaek"},{"name":"Koesan","link":"http://en.wikipedia.org/wiki/Koesan"},{"name":"Tangjin","link":"http://en.wikipedia.org/wiki/Tangjin"},{"name":"Kanghwa","link":"http://en.wikipedia.org/wiki/Kanghwa"},{"name":"ogcheongun","link":"http://en.wikipedia.org/wiki/ogcheongun"},{"name":"Santyoku","link":"http://en.wikipedia.org/wiki/Santyoku"}]},{"name":"KW","cityList":[{"name":"Ar Riqqah","link":"http://en.wikipedia.org/wiki/Ar+Riqqah"},{"name":"Janub as Surrah","link":"http://en.wikipedia.org/wiki/Janub+as+Surrah"},{"name":"Bayan","link":"http://en.wikipedia.org/wiki/Bayan%2C_Kuwait"},{"name":"As Salimiyah","link":"http://en.wikipedia.org/wiki/Salmiya"},{"name":"Al Manqaf","link":"http://en.wikipedia.org/wiki/Al+Manqaf"},{"name":"Al Mahbulah","link":"http://en.wikipedia.org/wiki/Al+Mahbulah"},{"name":"Al Jahra","link":"http://en.wikipedia.org/wiki/Al_Jahra"},{"name":"Al Fahahil","link":"http://en.wikipedia.org/wiki/Al+Fahahil"},{"name":"Al Fintas","link":"http://en.wikipedia.org/wiki/Al+Fintas"},{"name":"Ad Dasmah","link":"http://en.wikipedia.org/wiki/Ad+Dasmah"},{"name":"Salwa","link":"http://en.wikipedia.org/wiki/Salwa%2C_Kuwait"},{"name":"Ar Rabiyah","link":"http://en.wikipedia.org/wiki/Ar+Rabiyah"},{"name":"Sabah as Salim","link":"http://en.wikipedia.org/wiki/Sabah+as+Salim"}]},{"name":"KY","cityList":[{"name":"George Town","link":"http://en.wikipedia.org/wiki/George+Town"}]},{"name":"KZ","cityList":[{"name":"Qulsary","link":"http://en.wikipedia.org/wiki/Kulsary"},{"name":"Balyqshy","link":"http://en.wikipedia.org/wiki/Balyqshy"},{"name":"Lenger","link":"http://en.wikipedia.org/wiki/Lenger"},{"name":"Georgievka","link":"http://en.wikipedia.org/wiki/Georgievka"},{"name":"Zaysan","link":"http://en.wikipedia.org/wiki/Zaysan"},{"name":"Oktyabrsk","link":"http://en.wikipedia.org/wiki/Oktyabrsk"},{"name":"Karagandy","link":"http://en.wikipedia.org/wiki/Karagandy"},{"name":"Embi","link":"http://en.wikipedia.org/wiki/Embi"},{"name":"Aqsay","link":"http://en.wikipedia.org/wiki/Aksay%2C_West_Kazakhstan"},{"name":"Zhosaly","link":"http://en.wikipedia.org/wiki/Zhosaly"},{"name":"Zhangaqorghan","link":"http://en.wikipedia.org/wiki/Zhangaqorghan"},{"name":"Tasboget","link":"http://en.wikipedia.org/wiki/Tasboget"},{"name":"Energeticheskiy","link":"http://en.wikipedia.org/wiki/Energeticheskiy"},{"name":"Arys","link":"http://en.wikipedia.org/wiki/Arys%2C_Kazakhstan"},{"name":"Aral","link":"http://en.wikipedia.org/wiki/Aral%2C_Kazakhstan"},{"name":"Sarykemer","link":"http://en.wikipedia.org/wiki/Sarykemer"},{"name":"Oral","link":"http://en.wikipedia.org/wiki/Oral"},{"name":"Petropavlovsk","link":"http://en.wikipedia.org/wiki/Petropavlovsk"},{"name":"Kokshetau","link":"http://en.wikipedia.org/wiki/Kokshetau"},{"name":"Shchuchinsk","link":"http://en.wikipedia.org/wiki/Shchuchinsk"},{"name":"Shu","link":"http://en.wikipedia.org/wiki/Shu%2C_Kazakhstan"},{"name":"Burunday","link":"http://en.wikipedia.org/wiki/Burunday"},{"name":"Almaty","link":"http://en.wikipedia.org/wiki/Almaty"},{"name":"Taraz","link":"http://en.wikipedia.org/wiki/Taraz"},{"name":"Atyrau","link":"http://en.wikipedia.org/wiki/Atyrau"},{"name":"Pavlodar","link":"http://en.wikipedia.org/wiki/Pavlodar"},{"name":"Astana","link":"http://en.wikipedia.org/wiki/Astana"},{"name":"Ekibastuz","link":"http://en.wikipedia.org/wiki/Ekibastuz"},{"name":"Temirtau","link":"http://en.wikipedia.org/wiki/Temirtau"},{"name":"Semey","link":"http://en.wikipedia.org/wiki/Semey"},{"name":"Qyzylorda","link":"http://en.wikipedia.org/wiki/Qyzylorda"},{"name":"Abay","link":"http://en.wikipedia.org/wiki/Abay"},{"name":"Lisakovsk","link":"http://en.wikipedia.org/wiki/Lisakovsk"},{"name":"Zhetiqara","link":"http://en.wikipedia.org/wiki/Zhetiqara"},{"name":"Turar Ryskulov","link":"http://en.wikipedia.org/wiki/Turar+Ryskulov"},{"name":"Zhezqazghan","link":"http://en.wikipedia.org/wiki/Zhezqazghan"},{"name":"Qapshaghay","link":"http://en.wikipedia.org/wiki/Qapshaghay"},{"name":"Ridder","link":"http://en.wikipedia.org/wiki/Ridder"},{"name":"Zyryanovsk","link":"http://en.wikipedia.org/wiki/Zyryanovsk"},{"name":"Khromtau","link":"http://en.wikipedia.org/wiki/Khromtau"},{"name":"Talghar","link":"http://en.wikipedia.org/wiki/Talghar"},{"name":"Aqsu","link":"http://en.wikipedia.org/wiki/Aqsu"},{"name":"Stepnogorsk","link":"http://en.wikipedia.org/wiki/Stepnogorsk"},{"name":"Balqash","link":"http://en.wikipedia.org/wiki/Balqash"},{"name":"Ust-Kamenogorsk","link":"http://en.wikipedia.org/wiki/Ust-Kamenogorsk"},{"name":"Turkestan","link":"http://en.wikipedia.org/wiki/Turkestan"},{"name":"Qostanay","link":"http://en.wikipedia.org/wiki/Qostanay"},{"name":"Aqtobe","link":"http://en.wikipedia.org/wiki/Aqtobe"},{"name":"Ayteke Bi","link":"http://en.wikipedia.org/wiki/Ayteke+Bi"},{"name":"Tekeli","link":"http://en.wikipedia.org/wiki/Tekeli"},{"name":"Kentau","link":"http://en.wikipedia.org/wiki/Kentau"},{"name":"Atbasar","link":"http://en.wikipedia.org/wiki/Atbasar"},{"name":"Karatau","link":"http://en.wikipedia.org/wiki/Karatau"},{"name":"Shieli","link":"http://en.wikipedia.org/wiki/Shieli"},{"name":"Esik","link":"http://en.wikipedia.org/wiki/Esik"},{"name":"Makinsk","link":"http://en.wikipedia.org/wiki/Makinsk"},{"name":"Ush-Tyube","link":"http://en.wikipedia.org/wiki/Ush-Tyube"},{"name":"Saryaghash","link":"http://en.wikipedia.org/wiki/Saryaghash"},{"name":"Taldyqorghan","link":"http://en.wikipedia.org/wiki/Taldyqorghan"},{"name":"Arkalyk","link":"http://en.wikipedia.org/wiki/Arkalyk"},{"name":"Merke","link":"http://en.wikipedia.org/wiki/Merke"},{"name":"Zharkent","link":"http://en.wikipedia.org/wiki/Zharkent"},{"name":"Shemonaikha","link":"http://en.wikipedia.org/wiki/Shemonaikha"},{"name":"Baykonyr","link":"http://en.wikipedia.org/wiki/Baykonyr"},{"name":"Rudnyy","link":"http://en.wikipedia.org/wiki/Rudnyy"},{"name":"Shymkent","link":"http://en.wikipedia.org/wiki/Shymkent"},{"name":"Zhangatas","link":"http://en.wikipedia.org/wiki/Zhangatas"},{"name":"Shardara","link":"http://en.wikipedia.org/wiki/Shardara"},{"name":"Ayagoz","link":"http://en.wikipedia.org/wiki/Ayagoz"},{"name":"Sarkand","link":"http://en.wikipedia.org/wiki/Sarkand"},{"name":"Aktau","link":"http://en.wikipedia.org/wiki/Aktau"},{"name":"Sorang","link":"http://en.wikipedia.org/wiki/Sorang"},{"name":"Aksu","link":"http://en.wikipedia.org/wiki/Aksu"},{"name":"Taldyqorghan","link":"http://en.wikipedia.org/wiki/Taldyqorghan"}]}]